dispatcherd/__init__.py
dispatcherd/chunking.py
dispatcherd/cli.py
dispatcherd/config.py
dispatcherd/control.py
dispatcherd/factories.py
dispatcherd/protocols.py
dispatcherd/publish.py
dispatcherd/registry.py
dispatcherd/utils.py
dispatcherd/brokers/__init__.py
dispatcherd/brokers/pg_notify.py
dispatcherd/brokers/socket.py
dispatcherd/processors/blocker.py
dispatcherd/processors/delayer.py
dispatcherd/processors/params.py
dispatcherd/processors/queuer.py
dispatcherd/producers/__init__.py
dispatcherd/producers/base.py
dispatcherd/producers/brokered.py
dispatcherd/producers/control.py
dispatcherd/producers/on_start.py
dispatcherd/producers/scheduled.py
dispatcherd/service/asyncio_tasks.py
dispatcherd/service/control_tasks.py
dispatcherd/service/main.py
dispatcherd/service/metrics.py
dispatcherd/service/next_wakeup_runner.py
dispatcherd/service/pool.py
dispatcherd/service/process.py
dispatcherd/testing/__init__.py
dispatcherd/testing/asyncio.py
dispatcherd/testing/producers.py
dispatcherd/testing/subprocess.py
dispatcherd/testing/brokers/__init__.py
dispatcherd/testing/brokers/error_only.py
dispatcherd/testing/brokers/memory.py
dispatcherd/testing/brokers/noop.py
dispatcherd/worker/exceptions.py
dispatcherd/worker/target.py
dispatcherd/worker/task.py
dispatcherd-2026.1.14.dist-info/licenses/LICENSE
dispatcherd-2026.1.14.dist-info/METADATA
dispatcherd-2026.1.14.dist-info/WHEEL
dispatcherd-2026.1.14.dist-info/entry_points.txt
dispatcherd-2026.1.14.dist-info/top_level.txt
dispatcherd-2026.1.14.dist-info/RECORD
