Metadata-Version: 2.4
Name: dispatcherd
Version: 2026.1.14
Summary: An asyncio-based dispatcher for tasks in a worker pool.
Author-email: Alan Rominger <arominge@redhat.com.com>
License: Apache-2.0
Project-URL: Repository, https://github.com/ansible/dispatcherd
Keywords: asyncio,multiprocessing,dispatcher,dispatcherd,pg_notify,python
Classifier: Development Status :: 3 - Alpha
Classifier: Intended Audience :: Developers
Classifier: Programming Language :: Python :: 3
Classifier: Programming Language :: Python :: 3.12
Classifier: Programming Language :: Python :: 3.13
Classifier: Programming Language :: Python :: 3.14
License-File: LICENSE
Requires-Dist: pyyaml
Provides-Extra: pg-notify
Requires-Dist: psycopg>=3.2.4; extra == "pg-notify"
Provides-Extra: pg-notify-dev
Requires-Dist: psycopg[binary]>=3.2.4; extra == "pg-notify-dev"
Provides-Extra: pg-notify-prod
Requires-Dist: psycopg[c]>=3.2.4; extra == "pg-notify-prod"
Provides-Extra: metrics
Requires-Dist: prometheus-client; extra == "metrics"
Dynamic: license-file
